{
"type": "FeatureCollection",
"name": "祁漫塔格山",
"crs": { "type": "name", "properties": { "name": "urn:ogc:def:crs:OGC:1.3:CRS84" } },
"features": [
{ "type": "Feature", "properties": { "boundary_name": "祁漫塔格山", "side_width_km": 50.0, "source_id": 350334, "full_name": "新疆维吾尔自治区巴音郭楞蒙古自治州若羌县祁曼塔格乡祁曼塔格村民委员会", "raw_name": "祁曼塔格村民委员会", "clean_name": "祁曼塔格村", "name_body": "祁曼塔格", "part": "name_body", "char": "塔", "feature_id": "name_body_塔", "small_feature": "name_body_塔", "big_feature": "宗教建筑类", "semantic_type": "宗教建筑类", "community_id": "C010", "community_features": "name_body_塔", "side": "B", "dist_m": 11654.825494013248, "station_m": 95304.797187929071, "raw_station_m": 95304.797187929071, "station_clip_abs_offset_m": 0.0, "clip_direction": "inside", "effective_clip": false }, "geometry": { "type": "Point", "coordinates": [ 90.343913572526958, 37.308568546253817 ] } },
{ "type": "Feature", "properties": { "boundary_name": "祁漫塔格山", "side_width_km": 50.0, "source_id": 350330, "full_name": "新疆维吾尔自治区巴音郭楞蒙古自治州若羌县铁木里克乡拉配泉村民委员会", "raw_name": "拉配泉村民委员会", "clean_name": "拉配泉村", "name_body": "拉配泉", "part": "name_body", "char": "泉", "feature_id": "name_body_泉", "small_feature": "name_body_泉", "big_feature": "水文环境类", "semantic_type": "水文环境类", "community_id": "C045", "community_features": "name_body_泉", "side": "A", "dist_m": 13680.238068188863, "station_m": 26215.996379649441, "raw_station_m": 26215.996379649441, "station_clip_abs_offset_m": 0.0, "clip_direction": "inside", "effective_clip": false }, "geometry": { "type": "Point", "coordinates": [ 89.798623638602123, 37.807137787086155 ] } },
{ "type": "Feature", "properties": { "boundary_name": "祁漫塔格山", "side_width_km": 50.0, "source_id": 350331, "full_name": "新疆维吾尔自治区巴音郭楞蒙古自治州若羌县铁木里克乡玉泉村民委员会", "raw_name": "玉泉村民委员会", "clean_name": "玉泉村", "name_body": "玉泉", "part": "name_body", "char": "泉", "feature_id": "name_body_泉", "small_feature": "name_body_泉", "big_feature": "水文环境类", "semantic_type": "水文环境类", "community_id": "C045", "community_features": "name_body_泉", "side": "A", "dist_m": 13680.238068188863, "station_m": 26215.996379649441, "raw_station_m": 26215.996379649441, "station_clip_abs_offset_m": 0.0, "clip_direction": "inside", "effective_clip": false }, "geometry": { "type": "Point", "coordinates": [ 89.798623638602123, 37.807137787086155 ] } },
{ "type": "Feature", "properties": { "boundary_name": "祁漫塔格山", "side_width_km": 50.0, "source_id": 350328, "full_name": "新疆维吾尔自治区巴音郭楞蒙古自治州若羌县铁木里克乡铁木里克村民委员会", "raw_name": "铁木里克村民委员会", "clean_name": "铁木里克村", "name_body": "铁木里克", "part": "name_body", "char": "里", "feature_id": "name_body_里", "small_feature": "name_body_里", "big_feature": "聚落形态类", "semantic_type": "聚落形态类", "community_id": "C056", "community_features": "name_body_里", "side": "A", "dist_m": 13680.238068188863, "station_m": 26215.996379649441, "raw_station_m": 26215.996379649441, "station_clip_abs_offset_m": 0.0, "clip_direction": "inside", "effective_clip": false }, "geometry": { "type": "Point", "coordinates": [ 89.798623638602123, 37.807137787086155 ] } },
{ "type": "Feature", "properties": { "boundary_name": "祁漫塔格山", "side_width_km": 50.0, "source_id": 350329, "full_name": "新疆维吾尔自治区巴音郭楞蒙古自治州若羌县铁木里克乡白干湖村民委员会", "raw_name": "白干湖村民委员会", "clean_name": "白干湖村", "name_body": "白干湖", "part": "name_body", "char": "湖", "feature_id": "name_body_湖", "small_feature": "name_body_湖", "big_feature": "水文环境类", "semantic_type": "水文环境类", "community_id": "C047", "community_features": "name_body_湖", "side": "A", "dist_m": 13680.238068188863, "station_m": 26215.996379649441, "raw_station_m": 26215.996379649441, "station_clip_abs_offset_m": 0.0, "clip_direction": "inside", "effective_clip": false }, "geometry": { "type": "Point", "coordinates": [ 89.798623638602123, 37.807137787086155 ] } },
{ "type": "Feature", "properties": { "boundary_name": "祁漫塔格山", "side_width_km": 50.0, "source_id": 350329, "full_name": "新疆维吾尔自治区巴音郭楞蒙古自治州若羌县铁木里克乡白干湖村民委员会", "raw_name": "白干湖村民委员会", "clean_name": "白干湖村", "name_body": "白干湖", "part": "name_body", "char": "白", "feature_id": "name_body_白", "small_feature": "name_body_白", "big_feature": "民族文化类", "semantic_type": "民族文化类", "community_id": "C028", "community_features": "name_body_白", "side": "A", "dist_m": 13680.238068188863, "station_m": 26215.996379649441, "raw_station_m": 26215.996379649441, "station_clip_abs_offset_m": 0.0, "clip_direction": "inside", "effective_clip": false }, "geometry": { "type": "Point", "coordinates": [ 89.798623638602123, 37.807137787086155 ] } }
]
}
